{
 "kind": "FileDocument",
 "id": "README.md",
 "isDeleted": false,
 "rev": "",
 "description": "",
 "name": "README.md",
 "acl": {
  "kind": "Acl",
  "owner": "",
  "aces": []
 },
 "createdDate": {
  "kind": "Date",
  "value": ""
 },
 "lastModifiedDate": {
  "kind": "Date",
  "value": ""
 },
 "urls": [],
 "tags": [],
 "meta": [],
 "url": {
  "kind": "Url",
  "uri": ""
 },
 "version": "",
 "isPublic": false,
 "projectId": "",
 "folderId": "",
 "dataUri": "lfs/38/b2/03c681479e5883f74e133d341b16c5c1c39e6168152f61a83dd268e12226",
 "metadata": {
  "kind": "FileMetadata",
  "contentType": "",
  "cacheControl": "",
  "contentEncoding": "",
  "contentLanguage": "",
  "md5Hash": ""
 },
 "size": 3603
}